{
  "components": {
    "schemas": {
      "User": {
        "description": "Entité représentant un utilisateur applicatif.",
        "properties": {
          "displayName": {
            "type": "string"
          },
          "email": {
            "description": "Adresse e-mail de l'utilisateur, supposée unique.",
            "format": "email",
            "type": "string"
          },
          "id": {
            "description": "Identifiant unique de l'utilisateur.",
            "type": "string"
          }
        },
        "required": [
          "id",
          "email"
        ],
        "type": "object"
      }
    }
  },
  "info": {
    "title": "TSera API",
    "version": "1.0.0"
  },
  "openapi": "3.1.0",
  "paths": {},
  "x-tsera": {
    "generatedAt": "2024-01-01T00:00:00.000Z",
    "source": "project",
    "entities": [
      "User"
    ],
    "warning": "Auto-generated by TSera. Do not edit manually."
  }
}